myllannotator/__init__.py
myllannotator/main.py
myllannotator-0.1.6.dist-info/METADATA
myllannotator-0.1.6.dist-info/WHEEL
myllannotator-0.1.6.dist-info/entry_points.txt
myllannotator-0.1.6.dist-info/RECORD
