Metadata-Version: 2.4
Name: myllannotator
Version: 0.1.6
Summary: User-friendly tool for automated annotation of metadata with open-source LLM
Author-email: Alyssa Lu Lee <alyssalee@rutgers.edu>, Rohan Maddamsetti <rohan.maddamsetti@rutgers.edu>
Requires-Python: >=3.10
Requires-Dist: ollama>=0.6.1
Requires-Dist: tqdm>=4.41.0
